commemorate/__init__.py
commemorate/time.py
commemorate-0.0.0.1.1.dist-info/LICENSE
commemorate-0.0.0.1.1.dist-info/METADATA
commemorate-0.0.0.1.1.dist-info/WHEEL
commemorate-0.0.0.1.1.dist-info/top_level.txt
commemorate-0.0.0.1.1.dist-info/RECORD
